graphrag/__init__.py
graphrag/__main__.py
graphrag/py.typed
graphrag/api/__init__.py
graphrag/api/index.py
graphrag/api/prompt_tune.py
graphrag/api/query.py
graphrag/cache/__init__.py
graphrag/cache/factory.py
graphrag/cache/json_pipeline_cache.py
graphrag/cache/memory_pipeline_cache.py
graphrag/cache/noop_pipeline_cache.py
graphrag/cache/pipeline_cache.py
graphrag/callbacks/__init__.py
graphrag/callbacks/console_workflow_callbacks.py
graphrag/callbacks/llm_callbacks.py
graphrag/callbacks/noop_query_callbacks.py
graphrag/callbacks/noop_workflow_callbacks.py
graphrag/callbacks/query_callbacks.py
graphrag/callbacks/workflow_callbacks.py
graphrag/callbacks/workflow_callbacks_manager.py
graphrag/cli/__init__.py
graphrag/cli/index.py
graphrag/cli/initialize.py
graphrag/cli/main.py
graphrag/cli/prompt_tune.py
graphrag/cli/query.py
graphrag/config/__init__.py
graphrag/config/create_graphrag_config.py
graphrag/config/defaults.py
graphrag/config/embeddings.py
graphrag/config/enums.py
graphrag/config/environment_reader.py
graphrag/config/errors.py
graphrag/config/get_embedding_settings.py
graphrag/config/init_content.py
graphrag/config/load_config.py
graphrag/config/read_dotenv.py
graphrag/config/models/__init__.py
graphrag/config/models/basic_search_config.py
graphrag/config/models/cache_config.py
graphrag/config/models/chunking_config.py
graphrag/config/models/cluster_graph_config.py
graphrag/config/models/community_reports_config.py
graphrag/config/models/drift_search_config.py
graphrag/config/models/embed_graph_config.py
graphrag/config/models/extract_claims_config.py
graphrag/config/models/extract_graph_config.py
graphrag/config/models/extract_graph_nlp_config.py
graphrag/config/models/global_search_config.py
graphrag/config/models/graph_rag_config.py
graphrag/config/models/input_config.py
graphrag/config/models/language_model_config.py
graphrag/config/models/local_search_config.py
graphrag/config/models/prune_graph_config.py
graphrag/config/models/reporting_config.py
graphrag-2.6.0.dist-info/licenses/LICENSE
graphrag-2.6.0.dist-info/METADATA
graphrag-2.6.0.dist-info/WHEEL
graphrag-2.6.0.dist-info/entry_points.txt
graphrag-2.6.0.dist-info/top_level.txt
graphrag-2.6.0.dist-info/RECORD
