Metadata-Version: 2.4
Name: graphrag
Version: 2.6.0
Summary: GraphRAG: A graph-based retrieval-augmented generation (RAG) system.
Author: Mónica Carvajal
Author-email: Alonso Guevara Fernández <alonsog@microsoft.com>, Andrés Morales Esquivel <andresmor@microsoft.com>, Chris Trevino <chtrevin@microsoft.com>, David Tittsworth <datittsw@microsoft.com>, Dayenne de Souza <ddesouza@microsoft.com>, Derek Worthen <deworthe@microsoft.com>, Gaudy Blanco Meneses <gaudyb@microsoft.com>, Ha Trinh <trinhha@microsoft.com>, Jonathan Larson <jolarso@microsoft.com>, Josh Bradley <joshbradley@microsoft.com>, Kate Lytvynets <kalytv@microsoft.com>, Kenny Zhang <zhang
License-Expression: MIT
Project-URL: Source, https://github.com/microsoft/graphrag
Classifier: Programming Language :: Python :: 3
Classifier: Programming Language :: Python :: 3.10
Classifier: Programming Language :: Python :: 3.11
Classifier: Programming Language :: Python :: 3.12
Requires-Python: <3.13,>=3.10
License-File: LICENSE
Requires-Dist: environs>=11.0.0
Requires-Dist: azure-search-documents>=11.5.2
Requires-Dist: lancedb>=0.17.0
Requires-Dist: aiofiles>=24.1.0
Requires-Dist: fnllm[azure,openai]>=0.4.1
Requires-Dist: json-repair>=0.30.3
Requires-Dist: openai>=1.68.0
Requires-Dist: nltk==3.9.1
Requires-Dist: tiktoken>=0.11.0
Requires-Dist: numpy>=1.25.2
Requires-Dist: graspologic>=3.4.1
Requires-Dist: networkx>=3.4.2
Requires-Dist: pandas>=2.2.3
Requires-Dist: pyarrow>=17.0.0
Requires-Dist: umap-learn>=0.5.6
Requires-Dist: pyyaml>=6.0.2
Requires-Dist: python-dotenv>=1.0.1
Requires-Dist: pydantic>=2.10.3
Requires-Dist: devtools>=0.12.2
Requires-Dist: typing-extensions>=4.12.2
Requires-Dist: azure-cosmos>=4.9.0
Requires-Dist: azure-identity>=1.19.0
Requires-Dist: azure-storage-blob>=12.24.0
Requires-Dist: future>=1.0.0
Requires-Dist: typer>=0.16.0
Requires-Dist: tqdm>=4.67.1
Requires-Dist: textblob>=0.18.0.post0
Requires-Dist: spacy>=3.8.4
Requires-Dist: litellm>=1.77.1
Provides-Extra: dev
Requires-Dist: coverage>=7.6.9; extra == "dev"
Requires-Dist: ipykernel>=6.29.5; extra == "dev"
Requires-Dist: jupyter>=1.1.1; extra == "dev"
Requires-Dist: nbconvert>=7.16.4; extra == "dev"
Requires-Dist: poethepoet>=0.31.1; extra == "dev"
Requires-Dist: pandas-stubs>=2.3.0.250703; extra == "dev"
Requires-Dist: pyright>=1.1.390; extra == "dev"
Requires-Dist: pytest>=8.3.4; extra == "dev"
Requires-Dist: pytest-asyncio>=0.24.0; extra == "dev"
Requires-Dist: pytest-timeout>=2.3.1; extra == "dev"
Requires-Dist: ruff>=0.8.2; extra == "dev"
Requires-Dist: semversioner>=2.0.5; extra == "dev"
Requires-Dist: update-toml>=0.2.1; extra == "dev"
Requires-Dist: deptry>=0.21.1; extra == "dev"
Requires-Dist: mkdocs-material>=9.5.48; extra == "dev"
Requires-Dist: mkdocs-jupyter>=0.25.1; extra == "dev"
Requires-Dist: mkdocs-exclude-search>=0.6.6; extra == "dev"
Requires-Dist: pytest-dotenv>=0.5.2; extra == "dev"
Requires-Dist: mkdocs-typer>=0.0.3; extra == "dev"
Dynamic: license-file
